zipfanalysis/__init__.py
zipfanalysis/main.py
zipfanalysis/estimators/__init__.py
zipfanalysis/estimators/approximate_bayesian_computation.py
zipfanalysis/estimators/clauset.py
zipfanalysis/estimators/ols_regression_cdf.py
zipfanalysis/estimators/ols_regression_cdf_rank_histogram.py
zipfanalysis/estimators/ols_regression_pdf.py
zipfanalysis/preprocessing/__init__.py
zipfanalysis/preprocessing/preprocessing.py
zipfanalysis/tests/__init__.py
zipfanalysis/tests/test_abc_regression.py
zipfanalysis/tests/test_clauset.py
zipfanalysis/tests/test_ols_regression_cdf.py
zipfanalysis/tests/test_ols_regression_cdf_rank_histogram.py
zipfanalysis/tests/test_ols_regression_pdf.py
zipfanalysis/utilities/__init__.py
zipfanalysis/utilities/data_generators.py
zipfanalysis/utilities/probability_distributions.py
zipfanalysis-0.3.dist-info/DESCRIPTION.rst
zipfanalysis-0.3.dist-info/METADATA
zipfanalysis-0.3.dist-info/RECORD
zipfanalysis-0.3.dist-info/WHEEL
zipfanalysis-0.3.dist-info/metadata.json
zipfanalysis-0.3.dist-info/top_level.txt
