Metadata-Version: 2.0
Name: zipfanalysis
Version: 0.3
Summary: Tools for analysing Zipf's law from text samples
Home-page: https://github.com/chasmani/zipfanalysis
Author: Charlie Pilgrim
Author-email: pilgrimcharlie2@gmail.com
License: UNKNOWN
Platform: UNKNOWN
Classifier: Programming Language :: Python :: 3
Classifier: License :: OSI Approved :: MIT License
Classifier: Operating System :: OS Independent
Classifier: Topic :: Text Processing :: Linguistic
Requires-Python: >=3.6.9
